extractor/__init__.py
extractor/extractor.so
extractor/include/extractor/python/book.h
extractor/include/extractor/python/context.h
extractor/include/extractor/python/decimal.h
extractor/include/extractor/python/decimal128.h
extractor/include/extractor/python/extractor.h
extractor/include/extractor/python/fxpt128.h
extractor/include/extractor/python/rational64.h
extractor/include/extractor/python/rprice.h
extractor/tests/__init__.py
extractor/tests/arithmetic.py
extractor/tests/component.py
extractor/tools/__init__.py
extractor/tools/functions/__init__.py
extractor/tools/functions/piecewise.py
extractor/tools/statistics/__init__.py
extractor/tools/statistics/distribution.py
extractor/tools/visualization/__init__.py
extractor/tools/visualization/graph_dump_mod.py
extractor/tools/visualization/graph_viz_mod.py
featuremine_extractor-7.2.12.data/scripts/test-extractor-python
featuremine_extractor-7.2.12.dist-info/LICENSE
featuremine_extractor-7.2.12.dist-info/METADATA
featuremine_extractor-7.2.12.dist-info/WHEEL
featuremine_extractor-7.2.12.dist-info/top_level.txt
featuremine_extractor-7.2.12.dist-info/RECORD
