Metadata-Version: 2.1
Name: featuremine-extractor
Version: 7.2.12
Summary: Featuremine Extractor Package
Home-page: https://www.featuremine.com
Author: Featuremine Corporation
Author-email: support@featuremine.com
License: COPYRIGHT (c) 2022 by Featuremine Corporation
Platform: UNKNOWN
Classifier: Programming Language :: Python :: 3 :: Only
Requires-Dist: yamal
Requires-Dist: numpy (~=1.19)
Requires-Dist: pandas
Requires-Dist: graphviz
